oligopoolio/__init__.py
oligopoolio/main.py
oligopoolio/oligopools.py
oligopoolio/oligos.py
oligopoolio/primers.py
oligopoolio-0.0.4.data/data/LICENSE
oligopoolio-0.0.4.dist-info/LICENSE
oligopoolio-0.0.4.dist-info/METADATA
oligopoolio-0.0.4.dist-info/WHEEL
oligopoolio-0.0.4.dist-info/entry_points.txt
oligopoolio-0.0.4.dist-info/top_level.txt
oligopoolio-0.0.4.dist-info/RECORD
