Metadata-Version: 2.1
Name: oligopoolio
Version: 0.0.4
Home-page: https://github.com/arianemora/oligopoolio/
Author: Ariane Mora
Author-email: ariane.n.mora@gmail.com
License: GPL3
Project-URL: Bug Tracker, https://github.com/arianemora/oligopoolio/
Project-URL: Documentation, https://github.com/arianemora/oligopoolio/
Project-URL: Source Code, https://github.com/arianemora/oligopoolio/
Keywords: oligopools,protein-engineering
Classifier: Intended Audience :: Science/Research
Classifier: License :: OSI Approved :: GNU General Public License v3 (GPLv3)
Classifier: Natural Language :: English
Classifier: Operating System :: OS Independent
Classifier: Programming Language :: Python :: 3.8
Classifier: Topic :: Scientific/Engineering :: Bio-Informatics
Requires-Python: >=3.8
License-File: LICENSE
Requires-Dist: scikit-learn
Requires-Dist: dnaweaver
Requires-Dist: dnachisel
Requires-Dist: pdf-reports
Requires-Dist: sciutil
Requires-Dist: seaborn
Requires-Dist: statsmodels
Requires-Dist: biopython
Requires-Dist: primer3-py
Requires-Dist: pandas
Requires-Dist: numpy
Requires-Dist: gffutils
Requires-Dist: jupyterlab
